quarto/__init__.py
quarto/metadata.py
quarto/quarto.py
quarto/render.py
quarto-0.1.0.dist-info/LICENSE
quarto-0.1.0.dist-info/METADATA
quarto-0.1.0.dist-info/WHEEL
quarto-0.1.0.dist-info/top_level.txt
quarto-0.1.0.dist-info/RECORD
