Metadata-Version: 2.1
Name: quarto
Version: 0.1.0
Summary: Python Interface to 'Quarto' Markdown Publishing System
Home-page: https://github.com/quarto-dev/quarto-python
Author: JJ Allaire
Author-email: jj@rstudio.com
License: UNKNOWN
Platform: UNKNOWN
Classifier: Programming Language :: Python :: 3
Classifier: License :: OSI Approved :: GNU General Public License v2 or later (GPLv2+)
Classifier: Operating System :: OS Independent
Requires-Python: >=3.6
